Metadata-Version: 2.1
Name: sortme
Version: 0.0.1a0
Summary: Sort Me API wrapper for Python. Automate with a bang!
Home-page: https://github.com/sort-me/python-api
Author: Sort Me
Author-email: guys@sort-me.org
License: MIT
Keywords: sort-me.org sort-me sortme api sort_me sort me codeforces
Platform: UNKNOWN
